<!--
 Revision history:
     2010-08-26: Implemented, according to specification Schema, AJH, DTIC
	 2010-11-17: Updated, according to updated specification Schema, FZ, TIB
	 2011-01-17: Complete revision after community review, accroding to Schema version 2.0, FZ, TIB
-->
<resource xmlns:xsi="http://www.w3.org/2001/XMLSchema-instance" xsi:noNamespaceSchemaLocation="datacite-metadata-v2.0.xsd" lastMetadataUpdate="2006-05-04" metadataVersionNumber="1">
	<identifier identifierType="DOI">10.1594/WDCC/CCSRNIES_SRES_B2</identifier>
	<creators>
		<creator>
			<creatorName>Toru, Nozawa</creatorName>
		</creator>
		<creator>
			<creatorName>Utor, Awazon</creatorName>
			<nameIdentifier nameIdentifierScheme="ISNI">1422 4586 3573 0476</nameIdentifier>
		</creator>
	</creators>
	<titles>
		<title>National Institute for Environmental Studies and Center for Climate System Research Japan</title>
		<title titleType="Subtitle">A survey</title>
	</titles>
	<publisher>World Data Center for Climate (WDCC)</publisher>
	<publicationYear>2004</publicationYear>
	<subjects>
		<subject>Earth sciences and geology</subject>
	</subjects>
	<contributors>
		<contributor contributorType="DataManager">
			<contributorName>PANGAEA</contributorName>
		</contributor>
		<contributor contributorType="ContactPerson">
			<contributorName>Doe, John</contributorName>
			<nameIdentifier nameIdentifierScheme="ORCID">xyz789</nameIdentifier>
		</contributor>
	</contributors>
	<dates>
		<date dateType="Valid">2005-04-05</date>
		<date dateType="Accepted">2005-01-01</date>
	</dates>
	<language>en</language>
	<resourceType resourceTypeGeneral="Image">Animation</resourceType>
	<alternateIdentifiers>
		<alternateIdentifier alternateIdentifierType="ISBN">937-0-1234-56789-X</alternateIdentifier>
	</alternateIdentifiers>
	<relatedIdentifiers>
		<relatedIdentifier relatedIdentifierType="DOI" relationType="IsCitedBy">10.1234/testpub</relatedIdentifier>
		<relatedIdentifier relatedIdentifierType="URN" relationType="Cites">http://testing.ts/testpub</relatedIdentifier>
	</relatedIdentifiers>
	<sizes>
		<size>285 kb</size>
		<size>100 pages</size>
	</sizes>
	<formats>
		<format>text/plain</format>
	</formats>
	<version>1.0</version>
	<rights>Open Database License [ODbL]</rights>
	<descriptions>
		<description descriptionType="Other">
		The current xml-example for a DataCite record is the official example from the documentation.
		<br/>Please look on datcite.org to find the newest versions of sample data and schemas.
		</description>
	</descriptions>
</resource>
